[
  {
    "timeStamp": 2,
    "senderId": 8,
    "x": 0.17281335592269897,
    "y": 0.23895412683486938,
    "Recording": "ttCub3"
  },
  {
    "timeStamp": 500,
    "senderId": 8,
    "x": -0.2608506679534912,
    "y": 0.014764010906219482,
    "Recording": "ttCub3"
  },
  {
    "timeStamp": 1000,
    "senderId": 8,
    "x": 0.1424599289894104,
    "y": 0.006376206874847412,
    "Recording": "ttCub3"
  },
  {
    "timeStamp": 1500,
    "senderId": 8,
    "x": 0.37456560134887695,
    "y": 0.05542111396789551,
    "Recording": "ttCub3"
  },
  {
    "timeStamp": 2000,
    "senderId": 8,
    "x": -0.16670960187911987,
    "y": 0.09960347414016724,
    "Recording": "ttCub3"
  },
  {
    "timeStamp": 2501,
    "senderId": 8,
    "x": 0.41562867164611816,
    "y": 0.1560828685760498,
    "Recording": "ttCub3"
  },
  {
    "timeStamp": 3000,
    "senderId": 8,
    "x": 0.24699866771697998,
    "y": -0.09053775668144226,
    "Recording": "ttCub3"
  },
  {
    "timeStamp": 3500,
    "senderId": 8,
    "x": 0.07282030582427979,
    "y": -0.4447941780090332,
    "Recording": "ttCub3"
  },
  {
    "timeStamp": 4000,
    "senderId": 8,
    "x": 0.18419164419174194,
    "y": -0.1572306752204895,
    "Recording": "ttCub3"
  },
  {
    "timeStamp": 4501,
    "senderId": 8,
    "x": 0.3878917694091797,
    "y": 0.049359261989593506,
    "Recording": "ttCub3"
  },
  {
    "timeStamp": 5000,
    "senderId": 8,
    "x": -0.29921621084213257,
    "y": -0.17454421520233154,
    "Recording": "ttCub3"
  },
  {
    "timeStamp": 5500,
    "senderId": 8,
    "x": 0.3746986985206604,
    "y": -0.5091260671615601,
    "Recording": "ttCub3"
  },
  {
    "timeStamp": 6000,
    "senderId": 8,
    "x": -0.40316176414489746,
    "y": 0.1892644762992859,
    "Recording": "ttCub3"
  },
  {
    "timeStamp": 6500,
    "senderId": 8,
    "x": 0.48375505208969116,
    "y": 0.17643970251083374,
    "Recording": "ttCub3"
  },
  {
    "timeStamp": 7000,
    "senderId": 8,
    "x": 0.0843769907951355,
    "y": -0.02484506368637085,
    "Recording": "ttCub3"
  },
  {
    "timeStamp": 7500,
    "senderId": 8,
    "x": 0.04911184310913086,
    "y": -0.3868758976459503,
    "Recording": "ttCub3"
  },
  {
    "timeStamp": 8001,
    "senderId": 8,
    "x": 0.04952836036682129,
    "y": -0.37240922451019287,
    "Recording": "ttCub3"
  },
  {
    "timeStamp": 8501,
    "senderId": 8,
    "x": 0.03986901044845581,
    "y": 0.00633007287979126,
    "Recording": "ttCub3"
  },
  {
    "timeStamp": 9001,
    "senderId": 8,
    "x": 0.4765288829803467,
    "y": -0.556128740310669,
    "Recording": "ttCub3"
  },
  {
    "timeStamp": 9500,
    "senderId": 8,
    "x": -0.09968775510787964,
    "y": -0.06644433736801147,
    "Recording": "ttCub3"
  },
  {
    "timeStamp": 10001,
    "senderId": 8,
    "x": 0.02300053834915161,
    "y": -0.2617710828781128,
    "Recording": "ttCub3"
  },
  {
    "timeStamp": 10501,
    "senderId": 8,
    "x": -0.168931245803833,
    "y": -0.17050626873970032,
    "Recording": "ttCub3"
  },
  {
    "timeStamp": 11001,
    "senderId": 8,
    "x": 0.2754048705101013,
    "y": -0.398864209651947,
    "Recording": "ttCub3"
  },
  {
    "timeStamp": 11500,
    "senderId": 8,
    "x": 0.2444159984588623,
    "y": 0.28438830375671387,
    "Recording": "ttCub3"
  },
  {
    "timeStamp": 12001,
    "senderId": 8,
    "x": 0.028205275535583496,
    "y": 0.052092015743255615,
    "Recording": "ttCub3"
  },
  {
    "timeStamp": 12500,
    "senderId": 8,
    "x": -0.03783077001571655,
    "y": -0.12462377548217773,
    "Recording": "ttCub3"
  },
  {
    "timeStamp": 13000,
    "senderId": 8,
    "x": -0.01115405559539795,
    "y": 0.017055809497833252,
    "Recording": "ttCub3"
  },
  {
    "timeStamp": 13500,
    "senderId": 8,
    "x": 0.14247190952301025,
    "y": 0.10821926593780518,
    "Recording": "ttCub3"
  },
  {
    "timeStamp": 14000,
    "senderId": 8,
    "x": 0.04402363300323486,
    "y": -0.028461813926696777,
    "Recording": "ttCub3"
  },
  {
    "timeStamp": 14500,
    "senderId": 8,
    "x": -0.08321619033813477,
    "y": -0.2460288405418396,
    "Recording": "ttCub3"
  },
  {
    "timeStamp": 15000,
    "senderId": 8,
    "x": -0.33727991580963135,
    "y": -0.20655342936515808,
    "Recording": "ttCub3"
  },
  {
    "timeStamp": 15501,
    "senderId": 8,
    "x": -0.24027419090270996,
    "y": -0.06921303272247314,
    "Recording": "ttCub3"
  },
  {
    "timeStamp": 16001,
    "senderId": 8,
    "x": -0.1527770757675171,
    "y": -0.49141526222229004,
    "Recording": "ttCub3"
  },
  {
    "timeStamp": 16501,
    "senderId": 8,
    "x": -0.3946777582168579,
    "y": -0.043206751346588135,
    "Recording": "ttCub3"
  },
  {
    "timeStamp": 17000,
    "senderId": 8,
    "x": -0.2714017629623413,
    "y": 0.18697595596313477,
    "Recording": "ttCub3"
  },
  {
    "timeStamp": 17500,
    "senderId": 8,
    "x": 0.18726563453674316,
    "y": 0.2542172074317932,
    "Recording": "ttCub3"
  },
  {
    "timeStamp": 18000,
    "senderId": 8,
    "x": 0.24256032705307007,
    "y": -0.03783935308456421,
    "Recording": "ttCub3"
  },
  {
    "timeStamp": 18500,
    "senderId": 8,
    "x": 0.3344666361808777,
    "y": -0.1953025460243225,
    "Recording": "ttCub3"
  },
  {
    "timeStamp": 19001,
    "senderId": 8,
    "x": 0.49683278799057007,
    "y": -0.34022367000579834,
    "Recording": "ttCub3"
  },
  {
    "timeStamp": 19500,
    "senderId": 8,
    "x": -0.2622727155685425,
    "y": -0.5233104825019836,
    "Recording": "ttCub3"
  },
  {
    "timeStamp": 20000,
    "senderId": 8,
    "x": -0.07018733024597168,
    "y": -0.45133334398269653,
    "Recording": "ttCub3"
  },
  {
    "timeStamp": 20500,
    "senderId": 8,
    "x": -0.13197565078735352,
    "y": 0.19237899780273438,
    "Recording": "ttCub3"
  },
  {
    "timeStamp": 21000,
    "senderId": 8,
    "x": -0.31178420782089233,
    "y": -0.04163849353790283,
    "Recording": "ttCub3"
  },
  {
    "timeStamp": 21500,
    "senderId": 8,
    "x": 0.22821742296218872,
    "y": -0.36265915632247925,
    "Recording": "ttCub3"
  },
  {
    "timeStamp": 22000,
    "senderId": 8,
    "x": -0.02322697639465332,
    "y": -0.22900208830833435,
    "Recording": "ttCub3"
  },
  {
    "timeStamp": 22500,
    "senderId": 8,
    "x": -0.07235276699066162,
    "y": 0.16529810428619385,
    "Recording": "ttCub3"
  },
  {
    "timeStamp": 23000,
    "senderId": 8,
    "x": 0.07040119171142578,
    "y": 0.1353568434715271,
    "Recording": "ttCub3"
  },
  {
    "timeStamp": 23500,
    "senderId": 8,
    "x": 0.3201126456260681,
    "y": -0.1229412853717804,
    "Recording": "ttCub3"
  },
  {
    "timeStamp": 24001,
    "senderId": 8,
    "x": 0.38510292768478394,
    "y": -0.44976240396499634,
    "Recording": "ttCub3"
  },
  {
    "timeStamp": 24500,
    "senderId": 8,
    "x": 0.37904536724090576,
    "y": -0.4612196683883667,
    "Recording": "ttCub3"
  },
  {
    "timeStamp": 25000,
    "senderId": 8,
    "x": -0.15365219116210938,
    "y": -0.10655146837234497,
    "Recording": "ttCub3"
  },
  {
    "timeStamp": 25500,
    "senderId": 8,
    "x": 0.2836132049560547,
    "y": 0.263492226600647,
    "Recording": "ttCub3"
  },
  {
    "timeStamp": 26000,
    "senderId": 8,
    "x": 0.30820149183273315,
    "y": -0.17469194531440735,
    "Recording": "ttCub3"
  },
  {
    "timeStamp": 26500,
    "senderId": 8,
    "x": 0.037129342555999756,
    "y": -0.1597437858581543,
    "Recording": "ttCub3"
  },
  {
    "timeStamp": 27001,
    "senderId": 8,
    "x": 0.43839865922927856,
    "y": 0.16008859872817993,
    "Recording": "ttCub3"
  },
  {
    "timeStamp": 27500,
    "senderId": 8,
    "x": 0.44382762908935547,
    "y": -0.29329317808151245,
    "Recording": "ttCub3"
  },
  {
    "timeStamp": 28000,
    "senderId": 8,
    "x": -0.009335100650787354,
    "y": -0.5618751645088196,
    "Recording": "ttCub3"
  },
  {
    "timeStamp": 28501,
    "senderId": 8,
    "x": 0.18469542264938354,
    "y": -0.2474004328250885,
    "Recording": "ttCub3"
  },
  {
    "timeStamp": 29001,
    "senderId": 8,
    "x": 0.44615793228149414,
    "y": -0.24787122011184692,
    "Recording": "ttCub3"
  },
  {
    "timeStamp": 29500,
    "senderId": 8,
    "x": 0.32847756147384644,
    "y": -0.24183323979377747,
    "Recording": "ttCub3"
  },
  {
    "timeStamp": 30001,
    "senderId": 8,
    "x": -0.3395848870277405,
    "y": -0.3283049464225769,
    "Recording": "ttCub3"
  },
  {
    "timeStamp": 30500,
    "senderId": 8,
    "x": 0.14200061559677124,
    "y": -0.4202064871788025,
    "Recording": "ttCub3"
  },
  {
    "timeStamp": 31001,
    "senderId": 8,
    "x": 0.3702384829521179,
    "y": -0.31378498673439026,
    "Recording": "ttCub3"
  },
  {
    "timeStamp": 31501,
    "senderId": 8,
    "x": -0.3153002858161926,
    "y": -0.49243003129959106,
    "Recording": "ttCub3"
  },
  {
    "timeStamp": 32000,
    "senderId": 8,
    "x": -0.35717248916625977,
    "y": 0.08288496732711792,
    "Recording": "ttCub3"
  },
  {
    "timeStamp": 32500,
    "senderId": 8,
    "x": 0.22540676593780518,
    "y": -0.44136908650398254,
    "Recording": "ttCub3"
  },
  {
    "timeStamp": 33000,
    "senderId": 8,
    "x": 0.47265684604644775,
    "y": 0.2103850245475769,
    "Recording": "ttCub3"
  },
  {
    "timeStamp": 33500,
    "senderId": 8,
    "x": -0.07259422540664673,
    "y": -0.5143232941627502,
    "Recording": "ttCub3"
  },
  {
    "timeStamp": 34000,
    "senderId": 8,
    "x": -0.18857377767562866,
    "y": -0.4584603011608124,
    "Recording": "ttCub3"
  },
  {
    "timeStamp": 34501,
    "senderId": 8,
    "x": -0.16994434595108032,
    "y": -0.1473347544670105,
    "Recording": "ttCub3"
  },
  {
    "timeStamp": 35000,
    "senderId": 8,
    "x": 0.4420506954193115,
    "y": 0.13679790496826172,
    "Recording": "ttCub3"
  },
  {
    "timeStamp": 35500,
    "senderId": 8,
    "x": -0.36137646436691284,
    "y": 0.13181853294372559,
    "Recording": "ttCub3"
  },
  {
    "timeStamp": 36000,
    "senderId": 8,
    "x": -0.2778943181037903,
    "y": -0.35467350482940674,
    "Recording": "ttCub3"
  },
  {
    "timeStamp": 36501,
    "senderId": 8,
    "x": -0.26363641023635864,
    "y": 0.26748573780059814,
    "Recording": "ttCub3"
  },
  {
    "timeStamp": 37000,
    "senderId": 8,
    "x": -0.2699567675590515,
    "y": -0.09793135523796082,
    "Recording": "ttCub3"
  },
  {
    "timeStamp": 37500,
    "senderId": 8,
    "x": 0.015533626079559326,
    "y": 0.11143547296524048,
    "Recording": "ttCub3"
  },
  {
    "timeStamp": 38001,
    "senderId": 8,
    "x": 0.3031347393989563,
    "y": -0.38127151131629944,
    "Recording": "ttCub3"
  },
  {
    "timeStamp": 38500,
    "senderId": 8,
    "x": 0.12455040216445923,
    "y": -0.16218528151512146,
    "Recording": "ttCub3"
  },
  {
    "timeStamp": 39000,
    "senderId": 8,
    "x": 0.25780439376831055,
    "y": 0.21279889345169067,
    "Recording": "ttCub3"
  },
  {
    "timeStamp": 39501,
    "senderId": 8,
    "x": -0.025911927223205566,
    "y": -0.09925010800361633,
    "Recording": "ttCub3"
  },
  {
    "timeStamp": 40000,
    "senderId": 8,
    "x": 0.10104113817214966,
    "y": 0.2664912939071655,
    "Recording": "ttCub3"
  },
  {
    "timeStamp": 40500,
    "senderId": 8,
    "x": -0.12644332647323608,
    "y": -0.4872743487358093,
    "Recording": "ttCub3"
  },
  {
    "timeStamp": 41000,
    "senderId": 8,
    "x": 0.2925715446472168,
    "y": 0.16923439502716064,
    "Recording": "ttCub3"
  },
  {
    "timeStamp": 41500,
    "senderId": 8,
    "x": -0.2545074224472046,
    "y": -0.08570092916488647,
    "Recording": "ttCub3"
  },
  {
    "timeStamp": 42000,
    "senderId": 8,
    "x": 0.34847044944763184,
    "y": 0.16638511419296265,
    "Recording": "ttCub3"
  },
  {
    "timeStamp": 42500,
    "senderId": 8,
    "x": 0.04670935869216919,
    "y": -0.1609824001789093,
    "Recording": "ttCub3"
  },
  {
    "timeStamp": 43000,
    "senderId": 8,
    "x": -0.08823519945144653,
    "y": -0.47268009185791016,
    "Recording": "ttCub3"
  },
  {
    "timeStamp": 43500,
    "senderId": 8,
    "x": 0.352202832698822,
    "y": 0.10116469860076904,
    "Recording": "ttCub3"
  },
  {
    "timeStamp": 44000,
    "senderId": 8,
    "x": -0.300790011882782,
    "y": -0.15912184119224548,
    "Recording": "ttCub3"
  },
  {
    "timeStamp": 44501,
    "senderId": 8,
    "x": 0.012771248817443848,
    "y": -0.5624829530715942,
    "Recording": "ttCub3"
  },
  {
    "timeStamp": 45000,
    "senderId": 8,
    "x": 0.11908632516860962,
    "y": -0.34427013993263245,
    "Recording": "ttCub3"
  },
  {
    "timeStamp": 45500,
    "senderId": 8,
    "x": 0.494895875453949,
    "y": -0.10952329635620117,
    "Recording": "ttCub3"
  },
  {
    "timeStamp": 46000,
    "senderId": 8,
    "x": 0.3254019618034363,
    "y": 0.08237338066101074,
    "Recording": "ttCub3"
  },
  {
    "timeStamp": 46500,
    "senderId": 8,
    "x": 0.07504540681838989,
    "y": -0.34193262457847595,
    "Recording": "ttCub3"
  },
  {
    "timeStamp": 47000,
    "senderId": 8,
    "x": 0.2842252850532532,
    "y": -0.2824658751487732,
    "Recording": "ttCub3"
  },
  {
    "timeStamp": 47500,
    "senderId": 8,
    "x": -0.0014241337776184082,
    "y": -0.4656008780002594,
    "Recording": "ttCub3"
  },
  {
    "timeStamp": 48000,
    "senderId": 8,
    "x": -0.06650471687316895,
    "y": 0.2291279435157776,
    "Recording": "ttCub3"
  },
  {
    "timeStamp": 48500,
    "senderId": 8,
    "x": 0.0827743411064148,
    "y": 0.04493182897567749,
    "Recording": "ttCub3"
  },
  {
    "timeStamp": 49000,
    "senderId": 8,
    "x": -0.27778321504592896,
    "y": -0.12343910336494446,
    "Recording": "ttCub3"
  },
  {
    "timeStamp": 49500,
    "senderId": 8,
    "x": 0.13110381364822388,
    "y": -0.49774569272994995,
    "Recording": "ttCub3"
  },
  {
    "timeStamp": 50000,
    "senderId": 8,
    "x": 0.3230065107345581,
    "y": -0.29138556122779846,
    "Recording": "ttCub3"
  },
  {
    "timeStamp": 50500,
    "senderId": 8,
    "x": -0.34063029289245605,
    "y": 0.20643705129623413,
    "Recording": "ttCub3"
  },
  {
    "timeStamp": 51000,
    "senderId": 8,
    "x": -0.14351868629455566,
    "y": -0.5221002101898193,
    "Recording": "ttCub3"
  },
  {
    "timeStamp": 51500,
    "senderId": 8,
    "x": 0.4563339352607727,
    "y": -0.5098544359207153,
    "Recording": "ttCub3"
  },
  {
    "timeStamp": 52000,
    "senderId": 8,
    "x": -0.011243939399719238,
    "y": 0.12050575017929077,
    "Recording": "ttCub3"
  },
  {
    "timeStamp": 52500,
    "senderId": 8,
    "x": -0.43889176845550537,
    "y": -0.4033113121986389,
    "Recording": "ttCub3"
  },
  {
    "timeStamp": 53000,
    "senderId": 8,
    "x": 0.3218548893928528,
    "y": -0.26411086320877075,
    "Recording": "ttCub3"
  },
  {
    "timeStamp": 53501,
    "senderId": 8,
    "x": -0.13189923763275146,
    "y": 0.2529582381248474,
    "Recording": "ttCub3"
  },
  {
    "timeStamp": 54000,
    "senderId": 8,
    "x": -0.08983725309371948,
    "y": 0.031198203563690186,
    "Recording": "ttCub3"
  },
  {
    "timeStamp": 54500,
    "senderId": 8,
    "x": 0.44750308990478516,
    "y": -0.20028582215309143,
    "Recording": "ttCub3"
  },
  {
    "timeStamp": 55001,
    "senderId": 8,
    "x": -0.4691619873046875,
    "y": -0.028505027294158936,
    "Recording": "ttCub3"
  },
  {
    "timeStamp": 55501,
    "senderId": 8,
    "x": -0.1689387559890747,
    "y": -0.24677172303199768,
    "Recording": "ttCub3"
  },
  {
    "timeStamp": 56001,
    "senderId": 8,
    "x": 0.11364316940307617,
    "y": 0.08103471994400024,
    "Recording": "ttCub3"
  },
  {
    "timeStamp": 56500,
    "senderId": 8,
    "x": 0.15812981128692627,
    "y": 0.2030121088027954,
    "Recording": "ttCub3"
  },
  {
    "timeStamp": 57000,
    "senderId": 8,
    "x": -0.15295791625976562,
    "y": -0.20931124687194824,
    "Recording": "ttCub3"
  },
  {
    "timeStamp": 57500,
    "senderId": 8,
    "x": 0.10662257671356201,
    "y": 0.012781739234924316,
    "Recording": "ttCub3"
  },
  {
    "timeStamp": 58000,
    "senderId": 8,
    "x": -0.45056021213531494,
    "y": -0.4955434203147888,
    "Recording": "ttCub3"
  },
  {
    "timeStamp": 58501,
    "senderId": 8,
    "x": -0.28653794527053833,
    "y": -0.32069578766822815,
    "Recording": "ttCub3"
  },
  {
    "timeStamp": 59000,
    "senderId": 8,
    "x": 0.293192982673645,
    "y": -0.474448561668396,
    "Recording": "ttCub3"
  },
  {
    "timeStamp": 59500,
    "senderId": 8,
    "x": 0.2312214970588684,
    "y": -0.14474070072174072,
    "Recording": "ttCub3"
  },
  {
    "timeStamp": 60000,
    "senderId": 8,
    "x": -0.3057391047477722,
    "y": -0.17162922024726868,
    "Recording": "ttCub3"
  }
]